{
  "files": {
    "/.flexos/docs/001-vision.md": {
      "id": "blank-face-vision",
      "title": "Blank Face Vision Document",
      "description": "Vision for a platform connecting dog walkers and pet owners, named Blank Face.",
      "type": "doc",
      "subtype": "core",
      "status": "active",
      "tags": [
        "vision",
        "dog-walking",
        "pet-services",
        "marketplace",
        "community"
      ],
      "relatesTo": [],
      "updatedAt": "2026-03-14T21:45:46.249Z"
    }
  }
}